qsync/__init__.py
qsync/__main__.py
qsync/server.py
qsync-0.1.8.dist-info/METADATA
qsync-0.1.8.dist-info/WHEEL
qsync-0.1.8.dist-info/entry_points.txt
qsync-0.1.8.dist-info/top_level.txt
qsync-0.1.8.dist-info/RECORD
