Metadata-Version: 2.1
Name: qsync
Version: 0.1.8
Summary: The simplest one/two ways local/remote sync module in python.
Home-page: https://github.com/ThaaoBlues/qsync
Author: _ThaaoBlues_
Author-email: thaaoblues81@gmail.com
License: CC BY-NC-ND 4.0
Platform: UNKNOWN
Classifier: License :: Other/Proprietary License
Classifier: Programming Language :: Python
Classifier: Programming Language :: Python :: 3
Classifier: Programming Language :: Python :: 3.9
Requires-Python: >=3.6.0
Requires-Dist: flask
Requires-Dist: pyopenssl
Requires-Dist: requests
